spatial_centrality/__init__.py
spatial_centrality/_core.py
spatial_centrality-0.1.0.dist-info/METADATA
spatial_centrality-0.1.0.dist-info/WHEEL
spatial_centrality-0.1.0.dist-info/top_level.txt
spatial_centrality-0.1.0.dist-info/RECORD
