Metadata-Version: 2.4
Name: spatial_centrality
Version: 0.1.0
Summary: Spatial centrality scores for syntactic dependency trees
Author: marubekko
Classifier: Programming Language :: Python :: 3
Classifier: License :: OSI Approved :: MIT License
Requires-Python: >=3.7
Requires-Dist: networkx
Dynamic: author
Dynamic: classifier
Dynamic: description
Dynamic: description-content-type
Dynamic: requires-dist
Dynamic: requires-python
Dynamic: summary
